myportfolio_iol_py/__init__.py
myportfolio_iol_py/iol_py.py
myportfolio_iol_py/utils.py
myportfolio_iol_py-0.0.2.dist-info/METADATA
myportfolio_iol_py-0.0.2.dist-info/WHEEL
myportfolio_iol_py-0.0.2.dist-info/licenses/LICENSE
myportfolio_iol_py-0.0.2.dist-info/RECORD
