Metadata-Version: 2.3
Name: myportfolio_iol_py
Version: 0.0.2
Summary:  Es una librería de Python diseñada para obtener información de la API de Invertir Online.
Project-URL: Homepage, https://github.com/JRamos84/iol_py
Project-URL: Issues, https://github.com/pypa/sampleproject/issues
Author-email: José Florentino Ramos <joseph0001@gmail.com>
License-File: LICENSE
Classifier: License :: OSI Approved :: MIT License
Classifier: Operating System :: OS Independent
Classifier: Programming Language :: Python :: 3
Requires-Python: >=3.8
